geogee/__init__.py
geogee/common.py
geogee/geogee.py
geogee/utils.py
geogee-0.0.6.dist-info/licenses/LICENSE
geogee-0.0.6.dist-info/METADATA
geogee-0.0.6.dist-info/WHEEL
geogee-0.0.6.dist-info/dependency_links.txt
geogee-0.0.6.dist-info/top_level.txt
geogee-0.0.6.dist-info/RECORD
