Metadata-Version: 2.4
Name: geogee
Version: 0.0.6
Summary: A python package for geogee
Home-page: https://github.com/LyMot/geogee
Author: Ly Mot
Author-email: lymot101@gmail.com
License: MIT license
Keywords: geogee
Classifier: Intended Audience :: Developers
Classifier: License :: OSI Approved :: MIT License
Classifier: Natural Language :: English
Classifier: Programming Language :: Python :: 3
Classifier: Programming Language :: Python :: 3.8
Classifier: Programming Language :: Python :: 3.9
Classifier: Programming Language :: Python :: 3.10
Classifier: Programming Language :: Python :: 3.11
Requires-Python: >=3.8
License-File: LICENSE
Requires-Dist: ipyleaflet
Requires-Dist: Folium
Requires-Dist: mkdocs-material
Requires-Dist: mkdocstrings
Requires-Dist: mkdocstrings-python
Requires-Dist: mkdocs-jupyter
Requires-Dist: pyshp
Dynamic: author
Dynamic: author-email
Dynamic: classifier
Dynamic: description
Dynamic: description-content-type
Dynamic: home-page
Dynamic: keywords
Dynamic: license
Dynamic: license-file
Dynamic: requires-dist
Dynamic: requires-python
Dynamic: summary
